LICENSE.txt
setup.py
AFRITON_Py.egg-info/PKG-INFO
AFRITON_Py.egg-info/SOURCES.txt
AFRITON_Py.egg-info/dependency_links.txt
AFRITON_Py.egg-info/top_level.txt
name_afrit/AFRI.py
name_afrit/OS.py
name_afrit/S_X.py
name_afrit/Taiwn.py
name_afrit/__init__.py